CHANGELOG.rst
MANIFEST.in
README.rst
setup.py
spynepi/__init__.py
spynepi/db.py
spynepi/main.py
spynepi.egg-info/PKG-INFO
spynepi.egg-info/SOURCES.txt
spynepi.egg-info/dependency_links.txt
spynepi.egg-info/entry_points.txt
spynepi.egg-info/requires.txt
spynepi.egg-info/top_level.txt
spynepi/const/__init__.py
spynepi/const/template/__init__.py
spynepi/const/template/download.html
spynepi/entity/__init__.py
spynepi/entity/html.py
spynepi/entity/project.py
spynepi/entity/root.py
spynepi/util/__init__.py
spynepi/util/description.py
spynepi/util/pypi/__init__.py
spynepi/util/pypi/upload/__init__.py
spynepi/util/pypi/upload/__main__.py