Metadata-Version: 1.1
Name: spynepi
Version: 0.5.5
Summary: This is a caching PyPI implementation that uses Spyne
Home-page: http://github.com/arskom/spynepi
Author: Ugurcan Ergun
Author-email: ugurcanergn@gmail.com
License: GPL
Keywords: pypi,spyne,wsgi,rpc,http
Platform: UNKNOWN
Classifier: Programming Language :: Python
Classifier: Programming Language :: Python :: 2.7
Classifier: Operating System :: OS Independent
Classifier: Natural Language :: English
Classifier: Intended Audience :: Developers
